MANIFEST.in
README.md
setup.py
api_docs/__init__.py
api_docs/admin.py
api_docs/choices.py
api_docs/models.py
api_docs/slugs.py
api_docs/urls.py
api_docs/views.py
api_docs/migrations/0001_initial.py
api_docs/migrations/0002_auto__add_parameter.py
api_docs/migrations/0003_auto__add_field_parameter_default_value.py
api_docs/migrations/0004_auto__add_field_parameter_get_or_url.py
api_docs/migrations/0005_auto__add_field_apimethod_display_url.py
api_docs/migrations/0006_auto__add_field_apimethod_published.py
api_docs/migrations/__init__.py
api_docs/static/api_docs/css/styles.css
api_docs/static/api_docs/img/bg_body.gif
api_docs/static/api_docs/img/css3buttons_backgrounds.png
api_docs/static/api_docs/img/css3buttons_icons.png
api_docs/static/api_docs/img/rss.png
api_docs/templates/.DS_Store
api_docs/templates/api_docs/.DS_Store
api_docs/templates/api_docs/apis.html
api_docs/templates/api_docs/base.html
api_docs/templates/api_docs/docs.js
django_api_docs.egg-info/PKG-INFO
django_api_docs.egg-info/SOURCES.txt
django_api_docs.egg-info/dependency_links.txt
django_api_docs.egg-info/not-zip-safe
django_api_docs.egg-info/top_level.txt
docs/Makefile
docs/build/doctrees/environment.pickle
docs/build/doctrees/help.doctree
docs/build/doctrees/index.doctree
docs/build/doctrees/installation.doctree
docs/build/doctrees/javascript.doctree
docs/build/doctrees/license.doctree
docs/build/doctrees/templatecustomization.doctree
docs/build/html/.buildinfo
docs/build/html/genindex.html
docs/build/html/help.html
docs/build/html/index.html
docs/build/html/installation.html
docs/build/html/javascript.html
docs/build/html/license.html
docs/build/html/objects.inv
docs/build/html/search.html
docs/build/html/searchindex.js
docs/build/html/templatecustomization.html
docs/build/html/_sources/help.txt
docs/build/html/_sources/index.txt
docs/build/html/_sources/installation.txt
docs/build/html/_sources/javascript.txt
docs/build/html/_sources/license.txt
docs/build/html/_sources/templatecustomization.txt
docs/build/html/_static/ajax-loader.gif
docs/build/html/_static/basic.css
docs/build/html/_static/comment-bright.png
docs/build/html/_static/comment-close.png
