Metadata-Version: 1.0
Name: django-api-docs
Version: 1.1.1
Summary: Interactive API Documentation
Home-page: http://github.com/dstegelman/django-interactive-api-docs
Author: Derek Stegelman
Author-email: dstegelman@gmail.com
License: MIT
Keywords: django-interactive-api-docs
Platform: UNKNOWN
Classifier: Development Status :: 5 - Production/Stable
Classifier: Environment :: Web Environment
Classifier: Intended Audience :: End Users/Desktop
Classifier: Natural Language :: English
Classifier: Operating System :: OS Independent
Classifier: Programming Language :: Python
Classifier: Topic :: Internet :: WWW/HTTP :: Dynamic Content :: CGI Tools/Libraries
Classifier: Topic :: Utilities
Classifier: License :: OSI Approved :: MIT License
